setup.cfg
setup.py
Statistical_Computation/Original.py
Statistical_Computation/__init__.py
Statistical_Computation.egg-info/PKG-INFO
Statistical_Computation.egg-info/SOURCES.txt
Statistical_Computation.egg-info/dependency_links.txt
Statistical_Computation.egg-info/requires.txt
Statistical_Computation.egg-info/top_level.txt