Metadata-Version: 1.0
Name: Statistical-Computation
Version: 1.5
Summary: Implementation of scalable k-means++
Home-page: https://github.com/susancherry/Statistical_Computation.git
Author: Susan Cherry
Author-email: susan.cherry@duke.edu
License: MIT
Platform: UNKNOWN
